lab06/hdl/command_fifo.sv
`timescale 1ns / 1ps
`default_nettype none
 
module command_fifo #(parameter DEPTH=16, parameter WIDTH=16)(
        input  wire                 clk,
        input  wire                 rst,
        input  wire                 write,
        input  wire [WIDTH-1:0]     command_in,
        output logic                full,
 
        output logic [WIDTH-1:0]    command_out,   // async (combinational) read
        input  wire                 read,
        output logic                empty
    );

    localparam int AW = $clog2(DEPTH);

    logic [AW-1:0] write_pointer;
    logic [AW-1:0] read_pointer;

    logic [WIDTH-1:0] fifo [0:DEPTH-1];

    logic [AW-1:0] write_pointer_plus1;
    assign write_pointer_plus1 = write_pointer + {{(AW-1){1'b0}}, 1'b1};

    always_comb begin
        empty = (write_pointer == read_pointer);
        full = (write_pointer_plus1 == read_pointer);
        command_out = fifo[read_pointer];
    end

    always_ff @(posedge clk) begin
        if (rst) begin
            write_pointer <= '0;
            read_pointer <= '0;
        end else begin
            if (write && !full) begin
                fifo[write_pointer] <= command_in;
                write_pointer <= write_pointer + {{(AW-1){1'b0}}, 1'b1};
            end

            if (read && !empty) begin
                read_pointer <= read_pointer + {{(AW-1){1'b0}}, 1'b1};
            end
        end
    end
 
endmodule
`default_nettype wire

lab06/sim/sim_build/dump.vcd
$date
	Wed Oct 15 16:26:18 2025
$end
$version
	Icarus Verilog
$end
$timescale
	1ps
$end
$scope module command_fifo $end
$var wire 1 ! clk $end
$var wire 16 " command_in [15:0] $end
$var wire 1 # read $end
$var wire 1 $ rst $end
$var wire 1 % write $end
$var wire 4 & write_pointer_plus1 [3:0] $end
$var parameter 32 ' AW $end
$var parameter 32 ( DEPTH $end
$var parameter 32 ) WIDTH $end
$var reg 16 * command_out [15:0] $end
$var reg 1 + empty $end
$var reg 1 , full $end
$var reg 4 - read_pointer [3:0] $end
$var reg 4 . write_pointer [3:0] $end
$upscope $end
$enddefinitions $end
$comment Show the parameter values. $end
$dumpall
b10000 )
b10000 (
b100 '
$end
#0
$dumpvars
b0 .
b0 -
0,
1+
bx *
b1 &
0%
1$
0#
b0 "
1!
$end
#5000
0!
#10000
1!
#15000
0!
#20000
1!
#25000
0!
#30000
1!
#35000
0!
#40000
0$
1!
#45000
0!
#50000
1%
b10001 "
1!
#55000
0!
#60000
b100010 "
b10001 *
0+
b10 &
b1 .
1!
#65000
0!
#70000
b110011 "
b11 &
b10 .
1!
#75000
0!
#80000
b1000100 "
b100 &
b11 .
1!
#85000
0!
#90000
0%
b101 &
b100 .
1!
#95000
0!
#100000
1!
#105000
0!
#110000
1#
1!
#115000
0!
#120000
0#
b100010 *
b1 -
1!
#125000
0!
#130000
1#
1!
#135000
0!
#140000
0#
b110011 *
b10 -
1!
#145000
0!
#150000
1#
1!
#155000
0!
#160000
0#
b1000100 *
b11 -
1!
#165000
0!
#170000
1#
1!
#175000
0!
#180000
0#
bx *
1+
b100 -
1!
#185000
0!
#190000
1%
b1010000000000000 "
1!
#195000
0!
#200000
b1010000000000001 "
b1010000000000000 *
0+
b110 &
b101 .
1!
#205000
0!
#210000
b1010000000000010 "
b111 &
b110 .
1!
#215000
0!
#220000
b1010000000000011 "
b1000 &
b111 .
1!
#225000
0!
#230000
b1010000000000100 "
b1001 &
b1000 .
1!
#235000
0!
#240000
b1010000000000101 "
b1010 &
b1001 .
1!
#245000
0!
#250000
b1010000000000110 "
b1011 &
b1010 .
1!
#255000
0!
#260000
b1010000000000111 "
b1100 &
b1011 .
1!
#265000
0!
#270000
b1010000000001000 "
b1101 &
b1100 .
1!
#275000
0!
#280000
b1010000000001001 "
b1110 &
b1101 .
1!
#285000
0!
#290000
b1010000000001010 "
b1111 &
b1110 .
1!
#295000
0!
#300000
b1010000000001011 "
b0 &
b1111 .
1!
#305000
0!
#310000
b1010000000001100 "
b1 &
b0 .
1!
#315000
0!
#320000
b1010000000001101 "
b10 &
b1 .
1!
#325000
0!
#330000
b1010000000001110 "
b11 &
b10 .
1!
#335000
0!
#340000
b1010000000001111 "
1,
b100 &
b11 .
1!
#345000
0!
#350000
0%
1!
#355000
0!
#360000
1!
#365000
0!
#370000
1#
1!
#375000
0!
#380000
0#
b1010000000000001 *
0,
b101 -
1!
#385000
0!
#390000
1#
1!
#395000
0!
#400000
0#
b1010000000000010 *
b110 -
1!
#405000
0!
#410000
1#
1!
#415000
0!
#420000
0#
b1010000000000011 *
b111 -
1!
#425000
0!
#430000
1!
#435000
0!
#440000
1#
1!
#445000
0!
#450000
0#
b1010000000000100 *
b1000 -
1!
#455000
0!
#460000
1#
1!
#465000
0!
#470000
0#
b1010000000000101 *
b1001 -
1!
#475000
0!
#480000
1#
1!
#485000
0!
#490000
0#
b1010000000000110 *
b1010 -
1!
#495000
0!
#500000
1#
1!
#505000
0!
#510000
0#
b1010000000000111 *
b1011 -
1!
#515000
0!
#520000
1#
1!
#525000
0!
#530000
0#
b1010000000001000 *
b1100 -
1!
#535000
0!
#540000
1#
1!
#545000
0!
#550000
0#
b1010000000001001 *
b1101 -
1!
#555000
0!
#560000
1#
1!
#565000
0!
#570000
0#
b1010000000001010 *
b1110 -
1!
#575000
0!
#580000
1#
1!
#585000
0!
#590000
0#
b1010000000001011 *
b1111 -
1!
#595000
0!
#600000
1#
1!
#605000
0!
#610000
0#
b1010000000001100 *
b0 -
1!
#615000
0!
#620000
1#
1!
#625000
0!
#630000
0#
b1010000000001101 *
b1 -
1!
#635000
0!
#640000
1#
1!
#645000
0!
#650000
0#
b1010000000001110 *
b10 -
1!
#655000
0!
#660000
1#
1!
#665000
0!
#670000
0#
b1000100 *
1+
b11 -
1!
#675000
0!
#680000
1#
1!
#685000
0!
#690000
0#
1!
#695000
0!
#700000
1!
#705000
0!
#710000
1#
1!
#715000
0!
#720000
0#
1!
#725000
0!
#730000
1#
1!
#735000
0!
#740000
0#
1!
#745000
0!
#750000
1!
#755000
0!
#760000
1%
b1100000100000000 "
1!
#765000
0!
#770000
b1100000100000001 "
b1100000100000000 *
0+
b101 &
b100 .
1!
#775000
0!
#780000
b1100000100000010 "
b110 &
b101 .
1!
#785000
0!
#790000
b1100000100000011 "
b111 &
b110 .
1!
#795000
0!
#800000
b1100000100000100 "
b1000 &
b111 .
1!
#805000
0!
#810000
b1100000100000101 "
b1001 &
b1000 .
1!
#815000
0!
#820000
b1100000100000110 "
b1010 &
b1001 .
1!
#825000
0!
#830000
b1100000100000111 "
b1011 &
b1010 .
1!
#835000
0!
#840000
b1100000100001000 "
b1100 &
b1011 .
1!
#845000
0!
#850000
b1100000100001001 "
b1101 &
b1100 .
1!
#855000
0!
#860000
b1100000100001010 "
b1110 &
b1101 .
1!
#865000
0!
#870000
b1100000100001011 "
b1111 &
b1110 .
1!
#875000
0!
#880000
b1100000100001100 "
b0 &
b1111 .
1!
#885000
0!
#890000
b1100000100001101 "
b1 &
b0 .
1!
#895000
0!
#900000
0%
b10 &
b1 .
1!
#905000
0!
#910000
1!
#915000
0!
#920000
1#
1!
#925000
0!
#930000
0#
b1100000100000001 *
b100 -
1!
#935000
0!
#940000
1#
1!
#945000
0!
#950000
0#
b1100000100000010 *
b101 -
1!
#955000
0!
#960000
1#
1!
#965000
0!
#970000
0#
b1100000100000011 *
b110 -
1!
#975000
0!
#980000
1#
1!
#985000
0!
#990000
0#
b1100000100000100 *
b111 -
1!
#995000
0!
#1000000
1#
1!
#1005000
0!
#1010000
0#
b1100000100000101 *
b1000 -
1!
#1015000
0!
#1020000
1%
b1101001000000000 "
1!
#1025000
0!
#1030000
b1101001000000001 "
b11 &
b10 .
1!
#1035000
0!
#1040000
b1101001000000010 "
b100 &
b11 .
1!
#1045000
0!
#1050000
b1101001000000011 "
b101 &
b100 .
1!
#1055000
0!
#1060000
b1101001000000100 "
b110 &
b101 .
1!
#1065000
0!
#1070000
0%
b111 &
b110 .
1!
#1075000
0!
#1080000
1!
#1085000
0!
#1090000
1#
1!
#1095000
0!
#1100000
0#
b1100000100000110 *
b1001 -
1!
#1105000
0!
#1110000
1#
1!
#1115000
0!
#1120000
0#
b1100000100000111 *
b1010 -
1!
#1125000
0!
#1130000
1#
1!
#1135000
0!
#1140000
0#
b1100000100001000 *
b1011 -
1!
#1145000
0!
#1150000
1#
1!
#1155000
0!
#1160000
0#
b1100000100001001 *
b1100 -
1!
#1165000
0!
#1170000
1#
1!
#1175000
0!
#1180000
0#
b1100000100001010 *
b1101 -
1!
#1185000
0!
#1190000
1#
1!
#1195000
0!
#1200000
0#
b1100000100001011 *
b1110 -
1!
#1205000
0!
#1210000
1#
1!
#1215000
0!
#1220000
0#
b1100000100001100 *
b1111 -
1!
#1225000
0!
#1230000
1#
1!
#1235000
0!
#1240000
0#
b1100000100001101 *
b0 -
1!
#1245000
0!
#1250000
1#
1!
#1255000
0!
#1260000
0#
b1101001000000000 *
b1 -
1!
#1265000
0!
#1270000
1#
1!
#1275000
0!
#1280000
0#
b1101001000000001 *
b10 -
1!
#1285000
0!
#1290000
1#
1!
#1295000
0!
#1300000
0#
b1101001000000010 *
b11 -
1!
#1305000
0!
#1310000
1#
1!
#1315000
0!
#1320000
0#
b1101001000000011 *
b100 -
1!
#1325000
0!
#1330000
1#
1!
#1335000
0!
#1340000
0#
b1101001000000100 *
b101 -
1!
#1345000
0!
#1350000
1#
1!
#1355000
0!
#1360000
0#
b1100000100000011 *
1+
b110 -
1!
